orgweb/Dockerfile
orgweb/__init__.py
orgweb/container.py
orgweb/main.py
orgweb/monitor.py
orgweb/org.py
orgweb/utils.py
orgweb/resources/install.el
orgweb/resources/site-start.el
orgweb-0.0.7.dist-info/LICENSE
orgweb-0.0.7.dist-info/METADATA
orgweb-0.0.7.dist-info/WHEEL
orgweb-0.0.7.dist-info/entry_points.txt
orgweb-0.0.7.dist-info/top_level.txt
orgweb-0.0.7.dist-info/RECORD
